[{"station_id": "EPA-53", "recorded_at": "2023-05-28 14:00:00", "date": "28-05-2023", "time": "14:00", "location": "Roscommon Town", "pm10": 14.57, "pm2_5": 7.462, "no2": null, "o3": null, "so2": null, "co": null, "status": "green"}, {"station_id": "EPA-53", "recorded_at": "2023-05-28 15:00:00", "date": "28-05-2023", "time": "15:00", "location": "Roscommon Town", "pm10": 11.65, "pm2_5": 6.127, "no2": null, "o3": null, "so2": null, "co": null, "status": "green"}, {"station_id": "EPA-53", "recorded_at": "2023-05-28 16:00:00", "date": "28-05-2023", "time": "16:00", "location": "Roscommon Town", "pm10": 7.277, "pm2_5": 3.816, "no2": null, "o3": null, "so2": null, "co": null, "status": "green"}, {"station_id": "EPA-53", "recorded_at": "2023-05-28 17:00:00", "date": "28-05-2023", "time": "17:00", "location": "Roscommon Town", "pm10": 10.62, "pm2_5": 6.287, "no2": null, "o3": null, "so2": null, "co": null, "status": "green"}, {"station_id": "EPA-53", "recorded_at": "2023-05-28 18:00:00", "date": "28-05-2023", "time": "18:00", "location": "Roscommon Town", "pm10": 10.88, "pm2_5": 6.463, "no2": null, "o3": null, "so2": null, "co": null, "status": "green"}, {"station_id": "EPA-53", "recorded_at": "2023-05-28 19:00:00", "date": "28-05-2023", "time": "19:00", "location": "Roscommon Town", "pm10": 10.56, "pm2_5": 6.118, "no2": null, "o3": null, "so2": null, "co": null, "status": "green"}, {"station_id": "EPA-53", "recorded_at": "2023-05-28 20:00:00", "date": "28-05-2023", "time": "20:00", "location": "Roscommon Town", "pm10": 10.91, "pm2_5": 6.142, "no2": null, "o3": null, "so2": null, "co": null, "status": "green"}, {"station_id": "EPA-53", "recorded_at": "2023-05-28 22:00:00", "date": "28-05-2023", "time": "22:00", "location": "Roscommon Town", "pm10": 9.523, "pm2_5": 5.616, "no2": null, "o3": null, "so2": null, "co": null, "status": "green"}, {"station_id": "EPA-53", "recorded_at": "2023-05-29 00:00:00", "date": "29-05-2023", "time": "00:00", "location": "Roscommon Town", "pm10": 10.58, "pm2_5": 5.46, "no2": null, "o3": null, "so2": null, "co": null, "status": "green"}, {"station_id": "EPA-53", "recorded_at": "2023-05-29 02:00:00", "date": "29-05-2023", "time": "02:00", "location": "Roscommon Town", "pm10": 8.916, "pm2_5": 5.001, "no2": null, "o3": null, "so2": null, "co": null, "status": "green"}, {"station_id": "EPA-53", "recorded_at": "2023-05-29 03:00:00", "date": "29-05-2023", "time": "03:00", "location": "Roscommon Town", "pm10": 10.02, "pm2_5": 5.536, "no2": null, "o3": null, "so2": null, "co": null, "status": "green"}, {"station_id": "EPA-53", "recorded_at": "2023-05-29 05:00:00", "date": "29-05-2023", "time": "05:00", "location": "Roscommon Town", "pm10": 11.33, "pm2_5": 5.765, "no2": null, "o3": null, "so2": null, "co": null, "status": "green"}]