[{"station_id": "EPA-72", "recorded_at": "2023-05-28 13:00:00", "date": "28-05-2023", "time": "13:00", "location": "Cork Harbour", "pm10": null, "pm2_5": null, "no2": null, "o3": null, "so2": 0.8722, "co": null, "status": "green"}, {"station_id": "EPA-72", "recorded_at": "2023-05-28 15:00:00", "date": "28-05-2023", "time": "15:00", "location": "Cork Harbour", "pm10": null, "pm2_5": null, "no2": null, "o3": null, "so2": 0.7066, "co": null, "status": "green"}, {"station_id": "EPA-72", "recorded_at": "2023-05-28 16:00:00", "date": "28-05-2023", "time": "16:00", "location": "Cork Harbour", "pm10": null, "pm2_5": null, "no2": null, "o3": null, "so2": 1.0703, "co": null, "status": "green"}, {"station_id": "EPA-72", "recorded_at": "2023-05-28 17:00:00", "date": "28-05-2023", "time": "17:00", "location": "Cork Harbour", "pm10": null, "pm2_5": null, "no2": null, "o3": null, "so2": 2.7259, "co": null, "status": "green"}, {"station_id": "EPA-72", "recorded_at": "2023-05-28 18:00:00", "date": "28-05-2023", "time": "18:00", "location": "Cork Harbour", "pm10": null, "pm2_5": null, "no2": null, "o3": null, "so2": 1.5965, "co": null, "status": "green"}, {"station_id": "EPA-72", "recorded_at": "2023-05-28 19:00:00", "date": "28-05-2023", "time": "19:00", "location": "Cork Harbour", "pm10": null, "pm2_5": null, "no2": null, "o3": null, "so2": 1.1767, "co": null, "status": "green"}, {"station_id": "EPA-72", "recorded_at": "2023-05-28 20:00:00", "date": "28-05-2023", "time": "20:00", "location": "Cork Harbour", "pm10": null, "pm2_5": null, "no2": null, "o3": null, "so2": 0.9136, "co": null, "status": "green"}, {"station_id": "EPA-72", "recorded_at": "2023-05-28 21:00:00", "date": "28-05-2023", "time": "21:00", "location": "Cork Harbour", "pm10": null, "pm2_5": null, "no2": null, "o3": null, "so2": 0.9077, "co": null, "status": "green"}, {"station_id": "EPA-72", "recorded_at": "2023-05-28 22:00:00", "date": "28-05-2023", "time": "22:00", "location": "Cork Harbour", "pm10": null, "pm2_5": null, "no2": null, "o3": null, "so2": 0.8929, "co": null, "status": "green"}, {"station_id": "EPA-72", "recorded_at": "2023-05-29 01:00:00", "date": "29-05-2023", "time": "01:00", "location": "Cork Harbour", "pm10": null, "pm2_5": null, "no2": null, "o3": null, "so2": null, "co": null, "status": "green"}, {"station_id": "EPA-72", "recorded_at": "2023-05-29 03:00:00", "date": "29-05-2023", "time": "03:00", "location": "Cork Harbour", "pm10": null, "pm2_5": null, "no2": null, "o3": null, "so2": 2.451, "co": null, "status": "green"}, {"station_id": "EPA-72", "recorded_at": "2023-05-29 05:00:00", "date": "29-05-2023", "time": "05:00", "location": "Cork Harbour", "pm10": null, "pm2_5": null, "no2": null, "o3": null, "so2": 2.2706, "co": null, "status": "green"}, {"station_id": "EPA-72", "recorded_at": "2023-05-29 06:00:00", "date": "29-05-2023", "time": "06:00", "location": "Cork Harbour", "pm10": null, "pm2_5": null, "no2": null, "o3": null, "so2": 2.1997, "co": null, "status": "green"}, {"station_id": "EPA-72", "recorded_at": "2023-05-29 07:00:00", "date": "29-05-2023", "time": "07:00", "location": "Cork Harbour", "pm10": null, "pm2_5": null, "no2": null, "o3": null, "so2": 2.1701, "co": null, "status": "green"}, {"station_id": "EPA-72", "recorded_at": "2023-05-29 08:00:00", "date": "29-05-2023", "time": "08:00", "location": "Cork Harbour", "pm10": null, "pm2_5": null, "no2": null, "o3": null, "so2": 2.4332, "co": null, "status": "green"}, {"station_id": "EPA-72", "recorded_at": "2023-05-29 09:00:00", "date": "29-05-2023", "time": "09:00", "location": "Cork Harbour", "pm10": null, "pm2_5": null, "no2": null, "o3": null, "so2": 2.3741, "co": null, "status": "green"}, {"station_id": "EPA-72", "recorded_at": "2023-05-29 10:00:00", "date": "29-05-2023", "time": "10:00", "location": "Cork Harbour", "pm10": null, "pm2_5": null, "no2": null, "o3": null, "so2": 2.5072, "co": null, "status": "green"}, {"station_id": "EPA-72", "recorded_at": "2023-05-29 12:00:00", "date": "29-05-2023", "time": "12:00", "location": "Cork Harbour", "pm10": null, "pm2_5": null, "no2": null, "o3": null, "so2": 2.6846, "co": null, "status": "green"}, {"station_id": "EPA-72", "recorded_at": "2023-05-29 13:00:00", "date": "29-05-2023", "time": "13:00", "location": "Cork Harbour", "pm10": null, "pm2_5": null, "no2": null, "o3": null, "so2": 2.516, "co": null, "status": "green"}, {"station_id": "EPA-72", "recorded_at": "2023-05-29 14:00:00", "date": "29-05-2023", "time": "14:00", "location": "Cork Harbour", "pm10": null, "pm2_5": null, "no2": null, "o3": null, "so2": 2.4865, "co": null, "status": "green"}, {"station_id": "EPA-72", "recorded_at": "2023-05-29 15:00:00", "date": "29-05-2023", "time": "15:00", "location": "Cork Harbour", "pm10": null, "pm2_5": null, "no2": null, "o3": null, "so2": 2.5367, "co": null, "status": "green"}, {"station_id": "EPA-72", "recorded_at": "2023-05-29 16:00:00", "date": "29-05-2023", "time": "16:00", "location": "Cork Harbour", "pm10": null, "pm2_5": null, "no2": null, "o3": null, "so2": 2.5308, "co": null, "status": "green"}, {"station_id": "EPA-72", "recorded_at": "2023-05-29 17:00:00", "date": "29-05-2023", "time": "17:00", "location": "Cork Harbour", "pm10": null, "pm2_5": null, "no2": null, "o3": null, "so2": 2.5988, "co": null, "status": "green"}, {"station_id": "EPA-72", "recorded_at": "2023-05-29 19:00:00", "date": "29-05-2023", "time": "19:00", "location": "Cork Harbour", "pm10": null, "pm2_5": null, "no2": null, "o3": null, "so2": 3.1073, "co": null, "status": "green"}, {"station_id": "EPA-72", "recorded_at": "2023-05-29 20:00:00", "date": "29-05-2023", "time": "20:00", "location": "Cork Harbour", "pm10": null, "pm2_5": null, "no2": null, "o3": null, "so2": 2.5131, "co": null, "status": "green"}, {"station_id": "EPA-72", "recorded_at": "2023-05-29 21:00:00", "date": "29-05-2023", "time": "21:00", "location": "Cork Harbour", "pm10": null, "pm2_5": null, "no2": null, "o3": null, "so2": 2.3771, "co": null, "status": "green"}, {"station_id": "EPA-72", "recorded_at": "2023-05-29 22:00:00", "date": "29-05-2023", "time": "22:00", "location": "Cork Harbour", "pm10": null, "pm2_5": null, "no2": null, "o3": null, "so2": 2.4273, "co": null, "status": "green"}, {"station_id": "EPA-72", "recorded_at": "2023-05-30 00:00:00", "date": "30-05-2023", "time": "00:00", "location": "Cork Harbour", "pm10": null, "pm2_5": null, "no2": null, "o3": null, "so2": 2.4746, "co": null, "status": "green"}, {"station_id": "EPA-72", "recorded_at": "2023-05-30 02:00:00", "date": "30-05-2023", "time": "02:00", "location": "Cork Harbour", "pm10": null, "pm2_5": null, "no2": null, "o3": null, "so2": 2.451, "co": null, "status": "green"}, {"station_id": "EPA-72", "recorded_at": "2023-05-30 03:00:00", "date": "30-05-2023", "time": "03:00", "location": "Cork Harbour", "pm10": null, "pm2_5": null, "no2": null, "o3": null, "so2": 2.3948, "co": null, "status": "green"}, {"station_id": "EPA-72", "recorded_at": "2023-05-30 05:00:00", "date": "30-05-2023", "time": "05:00", "location": "Cork Harbour", "pm10": null, "pm2_5": null, "no2": null, "o3": null, "so2": 2.4096, "co": null, "status": "green"}, {"station_id": "EPA-72", "recorded_at": "2023-05-30 06:00:00", "date": "30-05-2023", "time": "06:00", "location": "Cork Harbour", "pm10": null, "pm2_5": null, "no2": null, "o3": null, "so2": 2.5929, "co": null, "status": "green"}, {"station_id": "EPA-72", "recorded_at": "2023-05-30 07:00:00", "date": "30-05-2023", "time": "07:00", "location": "Cork Harbour", "pm10": null, "pm2_5": null, "no2": null, "o3": null, "so2": 2.5929, "co": null, "status": "green"}, {"station_id": "EPA-72", "recorded_at": "2023-05-30 08:00:00", "date": "30-05-2023", "time": "08:00", "location": "Cork Harbour", "pm10": null, "pm2_5": null, "no2": null, "o3": null, "so2": 2.7614, "co": null, "status": "green"}, {"station_id": "EPA-72", "recorded_at": "2023-05-30 09:00:00", "date": "30-05-2023", "time": "09:00", "location": "Cork Harbour", "pm10": null, "pm2_5": null, "no2": null, "o3": null, "so2": 2.6372, "co": null, "status": "green"}, {"station_id": "EPA-72", "recorded_at": "2023-05-30 10:00:00", "date": "30-05-2023", "time": "10:00", "location": "Cork Harbour", "pm10": null, "pm2_5": null, "no2": null, "o3": null, "so2": 2.8117, "co": null, "status": "green"}, {"station_id": "EPA-72", "recorded_at": "2023-05-30 12:00:00", "date": "30-05-2023", "time": "12:00", "location": "Cork Harbour", "pm10": null, "pm2_5": null, "no2": null, "o3": null, "so2": 2.6698, "co": null, "status": "green"}, {"station_id": "EPA-72", "recorded_at": "2023-05-30 14:00:00", "date": "30-05-2023", "time": "14:00", "location": "Cork Harbour", "pm10": null, "pm2_5": null, "no2": null, "o3": null, "so2": 2.4983, "co": null, "status": "green"}, {"station_id": "EPA-72", "recorded_at": "2023-05-30 15:00:00", "date": "30-05-2023", "time": "15:00", "location": "Cork Harbour", "pm10": null, "pm2_5": null, "no2": null, "o3": null, "so2": 2.6077, "co": null, "status": "green"}, {"station_id": "EPA-72", "recorded_at": "2023-05-30 16:00:00", "date": "30-05-2023", "time": "16:00", "location": "Cork Harbour", "pm10": null, "pm2_5": null, "no2": null, "o3": null, "so2": 2.8531, "co": null, "status": "green"}, {"station_id": "EPA-72", "recorded_at": "2023-05-30 17:00:00", "date": "30-05-2023", "time": "17:00", "location": "Cork Harbour", "pm10": null, "pm2_5": null, "no2": null, "o3": null, "so2": 2.8738, "co": null, "status": "green"}, {"station_id": "EPA-72", "recorded_at": "2023-05-30 18:00:00", "date": "30-05-2023", "time": "18:00", "location": "Cork Harbour", "pm10": null, "pm2_5": null, "no2": null, "o3": null, "so2": 2.7792, "co": null, "status": "green"}, {"station_id": "EPA-72", "recorded_at": "2023-05-30 19:00:00", "date": "30-05-2023", "time": "19:00", "location": "Cork Harbour", "pm10": null, "pm2_5": null, "no2": null, "o3": null, "so2": 3.0719, "co": null, "status": "green"}, {"station_id": "EPA-72", "recorded_at": "2023-05-30 20:00:00", "date": "30-05-2023", "time": "20:00", "location": "Cork Harbour", "pm10": null, "pm2_5": null, "no2": null, "o3": null, "so2": 2.8886, "co": null, "status": "green"}, {"station_id": "EPA-72", "recorded_at": "2023-05-30 21:00:00", "date": "30-05-2023", "time": "21:00", "location": "Cork Harbour", "pm10": null, "pm2_5": null, "no2": null, "o3": null, "so2": 2.5545, "co": null, "status": "green"}, {"station_id": "EPA-72", "recorded_at": "2023-05-30 22:00:00", "date": "30-05-2023", "time": "22:00", "location": "Cork Harbour", "pm10": null, "pm2_5": null, "no2": null, "o3": null, "so2": 2.7732, "co": null, "status": "green"}, {"station_id": "EPA-72", "recorded_at": "2023-05-31 00:00:00", "date": "31-05-2023", "time": "00:00", "location": "Cork Harbour", "pm10": null, "pm2_5": null, "no2": null, "o3": null, "so2": 2.9122, "co": null, "status": "green"}, {"station_id": "EPA-72", "recorded_at": "2023-05-31 02:00:00", "date": "31-05-2023", "time": "02:00", "location": "Cork Harbour", "pm10": null, "pm2_5": null, "no2": null, "o3": null, "so2": 2.6461, "co": null, "status": "green"}, {"station_id": "EPA-72", "recorded_at": "2023-05-31 03:00:00", "date": "31-05-2023", "time": "03:00", "location": "Cork Harbour", "pm10": null, "pm2_5": null, "no2": null, "o3": null, "so2": 2.7407, "co": null, "status": "green"}, {"station_id": "EPA-72", "recorded_at": "2023-05-31 06:00:00", "date": "31-05-2023", "time": "06:00", "location": "Cork Harbour", "pm10": null, "pm2_5": null, "no2": null, "o3": null, "so2": 2.4776, "co": null, "status": "green"}]