[{"station_id": "EPA-48", "recorded_at": "2023-05-28 14:00:00", "date": "28-05-2023", "time": "14:00", "location": "Phoenix Park, Dublin 8", "pm10": 15.7, "pm2_5": 7.733, "no2": null, "o3": null, "so2": null, "co": null, "status": "green"}, {"station_id": "EPA-48", "recorded_at": "2023-05-28 16:00:00", "date": "28-05-2023", "time": "16:00", "location": "Phoenix Park, Dublin 8", "pm10": 13.96, "pm2_5": 7.182, "no2": null, "o3": null, "so2": null, "co": null, "status": "green"}, {"station_id": "EPA-48", "recorded_at": "2023-05-28 17:00:00", "date": "28-05-2023", "time": "17:00", "location": "Phoenix Park, Dublin 8", "pm10": 14.45, "pm2_5": 7.284, "no2": null, "o3": null, "so2": null, "co": null, "status": "green"}, {"station_id": "EPA-48", "recorded_at": "2023-05-28 18:00:00", "date": "28-05-2023", "time": "18:00", "location": "Phoenix Park, Dublin 8", "pm10": 10.88, "pm2_5": 5.91, "no2": null, "o3": null, "so2": null, "co": null, "status": "green"}, {"station_id": "EPA-48", "recorded_at": "2023-05-28 19:00:00", "date": "28-05-2023", "time": "19:00", "location": "Phoenix Park, Dublin 8", "pm10": 11.91, "pm2_5": 6.351, "no2": null, "o3": null, "so2": null, "co": null, "status": "green"}, {"station_id": "EPA-48", "recorded_at": "2023-05-28 20:00:00", "date": "28-05-2023", "time": "20:00", "location": "Phoenix Park, Dublin 8", "pm10": 10.57, "pm2_5": 5.873, "no2": null, "o3": null, "so2": null, "co": null, "status": "green"}, {"station_id": "EPA-48", "recorded_at": "2023-05-28 22:00:00", "date": "28-05-2023", "time": "22:00", "location": "Phoenix Park, Dublin 8", "pm10": 14.36, "pm2_5": 7.473, "no2": null, "o3": null, "so2": null, "co": null, "status": "green"}, {"station_id": "EPA-48", "recorded_at": "2023-05-29 02:00:00", "date": "29-05-2023", "time": "02:00", "location": "Phoenix Park, Dublin 8", "pm10": 11.08, "pm2_5": 6.48, "no2": null, "o3": null, "so2": null, "co": null, "status": "green"}, {"station_id": "EPA-48", "recorded_at": "2023-05-29 04:00:00", "date": "29-05-2023", "time": "04:00", "location": "Phoenix Park, Dublin 8", "pm10": 8.073, "pm2_5": 5.337, "no2": null, "o3": null, "so2": null, "co": null, "status": "green"}, {"station_id": "EPA-48", "recorded_at": "2023-05-29 06:00:00", "date": "29-05-2023", "time": "06:00", "location": "Phoenix Park, Dublin 8", "pm10": 8.709, "pm2_5": 5.292, "no2": null, "o3": null, "so2": null, "co": null, "status": "green"}, {"station_id": "EPA-48", "recorded_at": "2023-05-29 08:00:00", "date": "29-05-2023", "time": "08:00", "location": "Phoenix Park, Dublin 8", "pm10": 19.44, "pm2_5": 11.28, "no2": null, "o3": null, "so2": null, "co": null, "status": "green"}, {"station_id": "EPA-48", "recorded_at": "2023-05-29 09:00:00", "date": "29-05-2023", "time": "09:00", "location": "Phoenix Park, Dublin 8", "pm10": 16.28, "pm2_5": 10.17, "no2": null, "o3": null, "so2": null, "co": null, "status": "green"}, {"station_id": "EPA-48", "recorded_at": "2023-05-29 10:00:00", "date": "29-05-2023", "time": "10:00", "location": "Phoenix Park, Dublin 8", "pm10": 15.09, "pm2_5": 7.617, "no2": null, "o3": null, "so2": null, "co": null, "status": "green"}, {"station_id": "EPA-48", "recorded_at": "2023-05-29 13:00:00", "date": "29-05-2023", "time": "13:00", "location": "Phoenix Park, Dublin 8", "pm10": 12.45, "pm2_5": 7.574, "no2": null, "o3": null, "so2": null, "co": null, "status": "green"}]